topsis_102203080/__init__.py
topsis_102203080/topsis_102203080.py
topsis_102203080-1.1.dist-info/METADATA
topsis_102203080-1.1.dist-info/WHEEL
topsis_102203080-1.1.dist-info/top_level.txt
topsis_102203080-1.1.dist-info/RECORD
