Metadata-Version: 2.1
Name: topsis-102203080
Version: 1.1
Summary: This is a package for TOPSIS score calculation
Author: Keshav
Requires-Dist: pandas>=1.0.0
Requires-Dist: numpy>=1.18.0
